.hgignore
COPYING.txt
setup.cfg
setup.py
SchevoWsgi.egg-info/PKG-INFO
SchevoWsgi.egg-info/SOURCES.txt
SchevoWsgi.egg-info/dependency_links.txt
SchevoWsgi.egg-info/entry_points.txt
SchevoWsgi.egg-info/not-zip-safe
SchevoWsgi.egg-info/requires.txt
SchevoWsgi.egg-info/top_level.txt
schevowsgi/__init__.py
schevowsgi/dbopener.py
schevowsgi/identity.py
