Metadata-Version: 1.0
Name: SchevoWsgi
Version: 1.0a1
Summary: Schevo tools for WSGI
Home-page: http://schevo.org/wiki/SchevoWsgi
Author: Orbtech, L.L.C. and contributors
Author-email: schevo@googlegroups.com
License: LGPL
Platform: UNIX
Platform: Windows
Classifier: Development Status :: 3 - Alpha
Classifier: Environment :: Web Environment
Classifier: Intended Audience :: Developers
Classifier: License :: OSI Approved :: GNU Library or Lesser General Public License (LGPL)
Classifier: Operating System :: OS Independent
Classifier: Programming Language :: Python
Classifier: Topic :: Database :: Database Engines/Servers
Classifier: Topic :: Internet :: WWW/HTTP :: WSGI :: Middleware
Classifier: Topic :: Software Development :: Libraries :: Application Frameworks
